wtt02/__about__.py
wtt02/__init__.py
wtt02/_env.py
wtt02/main.py
wtt02-0.3.7.dist-info/METADATA
wtt02-0.3.7.dist-info/WHEEL
wtt02-0.3.7.dist-info/licenses/LICENSE.txt
wtt02-0.3.7.dist-info/RECORD
