Metadata-Version: 2.1
Name: wtt02
Version: 0.3.7
Author-email: Trent Hauck <thauck@wheretrue.com>
License-Expression: MIT
License-File: LICENSE.txt
Classifier: Programming Language :: Python
Classifier: Programming Language :: Python :: 3.7
Classifier: Programming Language :: Python :: 3.8
Classifier: Programming Language :: Python :: 3.9
Classifier: Programming Language :: Python :: 3.10
Classifier: Programming Language :: Python :: 3.11
Requires-Python: >=3.7
Requires-Dist: duckdb==0.7.1
